INSTALL.txt
MANIFEST.in
README.txt
debian_changelog_template.txt
ideas.txt
setup.py
windows_postinstall.py
bin/hms_run_servers
bin/hms_topic_print
bin/lsholons
bin/lstopics
icecfg/icebox.xml
icecfg/icegrid.cfg
icehms.egg-info/PKG-INFO
icehms.egg-info/SOURCES.txt
icehms.egg-info/dependency_links.txt
icehms.egg-info/entry_points.txt
icehms.egg-info/top_level.txt
slices/.hms.ice.swp
slices/hms.ice
src/python/icehms/__init__.py
src/python/icehms/agentmanager.py
src/python/icehms/cleaner.py
src/python/icehms/holon.py
src/python/icehms/icemanager.py
src/python/icehms/tools.py