Metadata-Version: 1.0
Name: icehms
Version: 1.0alpha3
Summary: Thin Framework to Develop Holonic or Multi-Agent Systems
Home-page: git@github.com:oroulet/icehms.git
Author: Olivier R-D
Author-email: Olivier.roulet@gmail.com
License: GNU General Public License
Platform: UNKNOWN
